{"metadata":{"usedHelpers":[],"marked":[],"modules":{"imports":[],"exports":{"exported":[],"specifiers":[]}}},"options":{"filename":"/client/main.js","filenameRelative":"/client/main.js","env":{"development":{"plugins":[]}},"retainLines":false,"highlightCode":true,"suppressDeprecationMessages":false,"presets":[],"plugins":[[[],{"polyfill":false}],[[],null],[[],null],[[],{"allowTopLevelThis":true,"strict":false,"loose":true}],[[],null],[[],null],[[],null],[[],null],[[],null],[[],null],[[],null],[[],null],[[],null],[[],null],[[],null],[[],null],[[],null],[[],{"loose":true}],[[],{"loose":true}],[[],null],[[],{"loose":true}],[[],null],[[],null],[[],null],[[],null],[[],null],[[],null],[[],{"loose":true}],[[],null],[[],null],[[],null],[[],null],[[],null],[[],null],[[],null]],"ignore":[],"code":true,"metadata":true,"ast":false,"comments":true,"compact":false,"minified":false,"sourceMap":true,"sourceMaps":true,"sourceMapTarget":"/client/main.js.map","sourceFileName":"/client/main.js","babelrc":false,"sourceType":"module","moduleIds":false,"passPerPreset":false,"parserOpts":false,"generatorOpts":false,"basename":"main"},"ignored":false,"code":"module.import('/imports/startup/client');","ast":null,"map":{"version":3,"sources":["/client/main.js"],"names":["module","import"],"mappings":"AAAAA,OAAOC,MAAP,CAAc,yBAAd","file":"/client/main.js.map","sourcesContent":["import '/imports/startup/client';\n"]},"hash":"3525a52380db9d1e181cbeea705ee202397262f0"}
